aimz/__init__.py
aimz/_exceptions.py
aimz/mlflow/__init__.py
aimz/mlflow/autolog.py
aimz/mlflow/load.py
aimz/mlflow/log.py
aimz/mlflow/pyfunc.py
aimz/mlflow/save.py
aimz/model/__init__.py
aimz/model/_core.py
aimz/model/impact_model.py
aimz/model/kernel_spec.py
aimz/sampling/__init__.py
aimz/sampling/_forward.py
aimz/utils/__init__.py
aimz/utils/_format.py
aimz/utils/_kwargs.py
aimz/utils/_output.py
aimz/utils/_validation.py
aimz/utils/data/__init__.py
aimz/utils/data/_input_setup.py
aimz/utils/data/_sharding.py
aimz/utils/data/array_dataset.py
aimz/utils/data/array_loader.py
aimz-0.9.1.dist-info/licenses/LICENSE
aimz-0.9.1.dist-info/METADATA
aimz-0.9.1.dist-info/WHEEL
aimz-0.9.1.dist-info/top_level.txt
aimz-0.9.1.dist-info/RECORD
