Metadata-Version: 2.4
Name: aimz
Version: 0.9.1
Summary: Scalable probabilistic impact modeling
Author-email: Eunseop Kim <markean@pm.me>, Jirapat Samranvedhya <jirapat.samranvedhya@lilly.com>
Maintainer-email: Eunseop Kim <markean@pm.me>
License-Expression: Apache-2.0
Project-URL: source, https://github.com/markean/aimz
Project-URL: documentation, https://aimz.readthedocs.io/
Classifier: Development Status :: 3 - Alpha
Classifier: Intended Audience :: Science/Research
Classifier: Topic :: Scientific/Engineering
Classifier: Programming Language :: Python :: 3.11
Classifier: Programming Language :: Python :: 3.12
Classifier: Programming Language :: Python :: 3.13
Requires-Python: >=3.11
License-File: LICENSE
Requires-Dist: dask>=2025.7
Requires-Dist: jax>=0.8
Requires-Dist: numpyro>=0.19.0
Requires-Dist: scikit-learn>=1.6.1
Requires-Dist: xarray>=2025.7
Requires-Dist: zarr<4,>=3
Provides-Extra: dev
Requires-Dist: pre-commit>=4.3; extra == "dev"
Requires-Dist: pytest>=9; extra == "dev"
Requires-Dist: pytest-cov>=7; extra == "dev"
Requires-Dist: ruff>=0.14; extra == "dev"
Provides-Extra: gpu
Requires-Dist: jax[cuda13]>=0.7; extra == "gpu"
Provides-Extra: mlflow
Requires-Dist: mlflow>=3; extra == "mlflow"
Provides-Extra: docs
Requires-Dist: arviz-plots[matplotlib]>=0.6; extra == "docs"
Requires-Dist: flax>=0.12; extra == "docs"
Requires-Dist: jupyter-sphinx>=0.5; extra == "docs"
Requires-Dist: mlflow>=3; extra == "docs"
Requires-Dist: myst-parser>=4.0; extra == "docs"
Requires-Dist: pydata-sphinx-theme>=0.16; extra == "docs"
Requires-Dist: sphinx>=8.2; extra == "docs"
Requires-Dist: sphinx-copybutton>=0.5; extra == "docs"
Requires-Dist: sphinx-design>=0.6; extra == "docs"
Dynamic: license-file
